cli/__init__.py
cli/sfv_interface.py
cli/spectral_fit_viewer_cli_full.py
spectral_fit_viewer-0.0.1.dist-info/METADATA
spectral_fit_viewer-0.0.1.dist-info/WHEEL
spectral_fit_viewer-0.0.1.dist-info/entry_points.txt
spectral_fit_viewer-0.0.1.dist-info/top_level.txt
spectral_fit_viewer-0.0.1.dist-info/RECORD
