Metadata-Version: 2.1
Name: spectral-fit-viewer
Version: 0.0.1
Summary: Spectral Fit Viewer CLI
Home-page: UNKNOWN
Author: Cheyenne Nelson
Author-email: cnelson@picarro.com
Maintainer: Picarro
License: Copyright Picarro internal use only
Project-URL: Code, https://github.com/picarro/spectral-fit-viewer
Platform: UNKNOWN
Requires-Python: >=3.9
Requires-Dist: bokeh
Requires-Dist: docopt
Requires-Dist: matplotlib
Requires-Dist: scipy
Requires-Dist: litho-tracktool-fitter
